RsAreg/RsAreg.py
RsAreg/__init__.py
RsAreg/enums.py
RsAreg/repcap.py
RsAreg/CustomFiles/__init__.py
RsAreg/CustomFiles/events.py
RsAreg/CustomFiles/utilities.py
RsAreg/Implementations/FormatPy.py
RsAreg/Implementations/Kboard.py
RsAreg/Implementations/Memory.py
RsAreg/Implementations/__init__.py
RsAreg/Implementations/Calibration/Frequency.py
RsAreg/Implementations/Calibration/Tselected.py
RsAreg/Implementations/Calibration/__init__.py
RsAreg/Implementations/Calibration/All/Measure.py
RsAreg/Implementations/Calibration/All/__init__.py
RsAreg/Implementations/Calibration/Data/Factory.py
RsAreg/Implementations/Calibration/Data/__init__.py
RsAreg/Implementations/Calibration/Data/Update/__init__.py
RsAreg/Implementations/Calibration/Data/Update/Level/Force.py
RsAreg/Implementations/Calibration/Data/Update/Level/__init__.py
RsAreg/Implementations/Calibration/Delay/Shutdown.py
RsAreg/Implementations/Calibration/Delay/__init__.py
RsAreg/Implementations/Calibration/Level/Attenuator.py
RsAreg/Implementations/Calibration/Level/__init__.py
RsAreg/Implementations/Calibration/Roscillator/Data.py
RsAreg/Implementations/Calibration/Roscillator/Store.py
RsAreg/Implementations/Calibration/Roscillator/__init__.py
RsAreg/Implementations/Calibration/Selected/Measure.py
RsAreg/Implementations/Calibration/Selected/__init__.py
RsAreg/Implementations/Device/__init__.py
RsAreg/Implementations/Device/Settings/Backup.py
RsAreg/Implementations/Device/Settings/Restore.py
RsAreg/Implementations/Device/Settings/__init__.py
RsAreg/Implementations/Diagnostic/BgInfo.py
RsAreg/Implementations/Diagnostic/Service.py
RsAreg/Implementations/Diagnostic/__init__.py
RsAreg/Implementations/Diagnostic/Debug/Page.py
RsAreg/Implementations/Diagnostic/Debug/__init__.py
RsAreg/Implementations/Diagnostic/Eeprom/Customize.py
RsAreg/Implementations/Diagnostic/Eeprom/__init__.py
RsAreg/Implementations/Diagnostic/Eeprom/Bidentifier/Catalog.py
RsAreg/Implementations/Diagnostic/Eeprom/Bidentifier/__init__.py
RsAreg-4.80.71.dist-info/METADATA
RsAreg-4.80.71.dist-info/WHEEL
RsAreg-4.80.71.dist-info/top_level.txt
RsAreg-4.80.71.dist-info/RECORD
